[{"province": "Cả nước", "cases": "1,320,764", "deaths": "27,850", "newCases": "14,024"}, {"province": "TP. Hồ Chí Minh", "cases": "501,258", "deaths": "19,389", "newCases": "560"}, {"province": "Bình Dương", "cases": "290,285", "deaths": "3,201", "newCases": "77"}, {"province": "Đồng Nai", "cases": "97,081", "deaths": "1,313", "newCases": "216"}, {"province": "Tây Ninh", "cases": "72,183", "deaths": "623", "newCases": "943"}, {"province": "Đồng Tháp", "cases": "41,872", "deaths": "525", "newCases": "701"}, {"province": "Long An", "cases": "40,181", "deaths": "869", "newCases": "45"}, {"province": "Cần Thơ", "cases": "39,422", "deaths": "543", "newCases": "711"}, {"province": "Hà Nội", "cases": "38,726", "deaths": "98", "newCases": "1,948"}, {"province": "Tiền Giang", "cases": "32,880", "deaths": "899", "newCases": "134"}, {"province": "Cà Mau", "cases": "32,499", "deaths": "141", "newCases": "433"}, {"province": "An Giang", "cases": "31,648", "deaths": "904", "newCases": "213"}, {"province": "Khánh Hòa", "cases": "30,033", "deaths": "161", "newCases": "791"}, {"province": "Sóc Trăng", "cases": "29,153", "deaths": "302", "newCases": "223"}, {"province": "Kiên Giang", "cases": "29,097", "deaths": "489", "newCases": "204"}, {"province": "Vĩnh Long", "cases": "28,643", "deaths": "295", "newCases": "892"}, {"province": "Bạc Liêu", "cases": "27,606", "deaths": "242", "newCases": "595"}, {"province": "Bà Rịa - Vũng Tàu", "cases": "26,168", "deaths": "148", "newCases": "162"}, {"province": "Bến Tre", "cases": "25,103", "deaths": "163", "newCases": "281"}, {"province": "Bình Thuận", "cases": "24,970", "deaths": "271", "newCases": "140"}, {"province": "Bình Phước", "cases": "20,230", "deaths": "52", "newCases": "30"}, {"province": "Trà Vinh", "cases": "19,343", "deaths": "117", "newCases": "544"}, {"province": "Bình Định", "cases": "13,858", "deaths": "55", "newCases": "501"}, {"province": "Thừa Thiên Huế", "cases": "11,752", "deaths": "12", "newCases": "381"}, {"province": "Hậu Giang", "cases": "11,680", "deaths": "38", "newCases": "63"}, {"province": "Đà Nẵng", "cases": "11,039", "deaths": "108", "newCases": "86"}, {"province": "Đắk Lắk", "cases": "11,012", "deaths": "63", "newCases": "134"}, {"province": "Bắc Ninh", "cases": "10,240", "deaths": "17", "newCases": "326"}, {"province": "Lâm Đồng", "cases": "7,770", "deaths": "24", "newCases": "263"}, {"province": "Bắc Giang", "cases": "7,644", "deaths": "14", "newCases": "40"}, {"province": "Nghệ An", "cases": "7,455", "deaths": "34", "newCases": "93"}, {"province": "Thanh Hóa", "cases": "7,029", "deaths": "13", "newCases": "249"}, {"province": "Hà Giang", "cases": "6,669", "deaths": "6", "newCases": "122"}, {"province": "Gia Lai", "cases": "6,611", "deaths": "15", "newCases": "136"}, {"province": "Hải Phòng", "cases": "6,604", "deaths": "7", "newCases": "931"}, {"province": "Phú Yên", "cases": "6,161", "deaths": "47", "newCases": "112"}, {"province": "Ninh Thuận", "cases": "5,506", "deaths": "52", "newCases": "56"}, {"province": "Quảng Ngãi", "cases": "5,167", "deaths": "25", "newCases": "201"}, {"province": "Quảng Ngãi", "cases": "5,167", "deaths": "25", "newCases": "201"}, {"province": "Đắk Nông", "cases": "4,584", "deaths": "13", "newCases": "98"}, {"province": "Hưng Yên", "cases": "4,314", "deaths": "2", "newCases": "234"}, {"province": "Quảng Bình", "cases": "3,536", "deaths": "8", "newCases": "14"}, {"province": "Nam Định", "cases": "3,022", "deaths": "2", "newCases": "78"}, {"province": "Hải Dương", "cases": "2,937", "deaths": "1", "newCases": "0"}, {"province": "Phú Thọ", "cases": "2,840", "deaths": "3", "newCases": "50"}, {"province": "Quảng Ninh", "cases": "2,736", "deaths": "1", "newCases": "103"}, {"province": "Vĩnh Phúc", "cases": "2,638", "deaths": "6", "newCases": "85"}, {"province": "Thái Bình", "cases": "2,439", "deaths": "0", "newCases": "42"}, {"province": "Hà Nam", "cases": "2,085", "deaths": "0", "newCases": "98"}, {"province": "Quảng Trị", "cases": "1,894", "deaths": "4", "newCases": "53"}, {"province": "Hà Tĩnh", "cases": "1,572", "deaths": "5", "newCases": "18"}, {"province": "Thái Nguyên", "cases": "1,572", "deaths": "1", "newCases": "59"}, {"province": "Lạng Sơn", "cases": "1,326", "deaths": "5", "newCases": "0"}, {"province": "Hoà Bình", "cases": "1,225", "deaths": "3", "newCases": "45"}, {"province": "Tuyên Quang", "cases": "974", "deaths": "0", "newCases": "28"}, {"province": "Sơn La", "cases": "863", "deaths": "0", "newCases": "126"}, {"province": "Kon Tum", "cases": "832", "deaths": "0", "newCases": "24"}, {"province": "Điện Biên", "cases": "573", "deaths": "0", "newCases": "9"}, {"province": "Yên Bái", "cases": "557", "deaths": "0", "newCases": "21"}, {"province": "Ninh Bình", "cases": "525", "deaths": "0", "newCases": "0"}, {"province": "Lào Cai", "cases": "425", "deaths": "0", "newCases": "19"}, {"province": "Cao Bằng", "cases": "411", "deaths": "1", "newCases": "22"}, {"province": "Lai Châu", "cases": "85", "deaths": "0", "newCases": "8"}, {"province": "Bắc Kạn", "cases": "50", "deaths": "0", "newCases": "0"}]